{IsEmpty:0b,InventoryHolder:{Zcoord:-9,cosmeticarmor:[],PlayerName:[],Ycoord:56,Xcoord:95,bauble:[{Slot:0b,ForgeCaps:{"astralsorcery:cap_item_amulet_holder":{}},id:"thermalexpansion:reservoir",Count:1b,tag:{},Damage:0s},{Slot:1b,ForgeCaps:{"astralsorcery:cap_item_amulet_holder":{}},id:"cyclicmagic:charm_void",Count:1b,tag:{},Damage:4s}],Timestamp:[],vanilla:[{Slot:0b,ForgeCaps:{"astralsorcery:cap_item_amulet_holder":{}},id:"tconstruct:pickaxe",Count:1b,tag:{StatsOriginal:{AttackSpeedMultiplier:1.0f,MiningSpeed:9.0f,FreeModifiers:3,Durability:619,HarvestLevel:4,Attack:3.075f},Stats:{AttackSpeedMultiplier:1.0f,MiningSpeed:9.0f,FreeModifiers:4,Durability:619,HarvestLevel:4,Attack:3.075f},Special:{Categories:["harvest","aoe","tool"]},TinkerData:{Materials:["wood","cobalt","ma.prosperity"],Modifiers:["toolleveling"]},Modifiers:[{identifier:"ecological",color:-7444965,level:1},{identifier:"momentum",color:-14122284,level:1},{identifier:"writable",color:-6044219,level:1,writable1:1b},{identifier:"toolleveling",color:16777215,level:1}],Traits:["ecological","momentum","writable1","toolleveling"]},Damage:0s},{Slot:2b,id:"mob_grinding_utils:saw",Count:1b,Damage:0s},{Slot:3b,ForgeCaps:{"astralsorcery:cap_item_amulet_holder":{}},id:"tconstruct:book",Count:1b,Damage:0s},{Slot:4b,ForgeCaps:{"astralsorcery:cap_item_amulet_holder":{}},id:"betterbuilderswands:wanddiamond",Count:1b,tag:{bbw:{lastBlock:"tconstruct:seared[type=brick]",lastItemBlock:"tconstruct:seared",lastPlaced:[I;105,73,115,105,73,114,105,73,116,106,73,114,105,73,117,107,73,114,105,73,118,106,73,118,108,73,114,107,73,118,109,73,114,109,73,115,108,73,118,109,73,116,109,73,118,109,73,117],lastBlockMeta:3,fluidmask:1s,lastPerBlock:1,mask:7s}},Damage:989s},{Slot:5b,id:"minecraft:dirt",Count:58b,Damage:0s},{Slot:6b,id:"mob_grinding_utils:entity_conveyor",Count:12b,Damage:0s},{Slot:7b,ForgeCaps:{"astralsorcery:cap_item_amulet_holder":{}},id:"storagenetwork:remote",Count:1b,tag:{bound:1b,dim:0,sort:"NAME",c0:{id:"minecraft:air",Count:0b,Damage:0s},c1:{id:"minecraft:air",Count:0b,Damage:0s},c2:{id:"minecraft:air",Count:0b,Damage:0s},c3:{id:"minecraft:air",Count:0b,Damage:0s},c4:{id:"minecraft:air",Count:0b,Damage:0s},c5:{id:"minecraft:air",Count:0b,Damage:0s},c6:{id:"minecraft:air",Count:0b,Damage:0s},c7:{id:"minecraft:air",Count:0b,Damage:0s},c8:{id:"minecraft:air",Count:0b,Damage:0s},x:102,y:68,z:110},Damage:1s},{Slot:8b,id:"minecraft:torch",Count:62b,Damage:0s},{Slot:9b,id:"lodsofemone:coin_small",Count:42b,tag:{value:25L},Damage:0s},{Slot:10b,id:"lodsofemone:coin_small",Count:46b,tag:{value:50L},Damage:0s},{Slot:11b,id:"lodsofemone:coin_big",Count:7b,tag:{value:200L},Damage:0s},{Slot:12b,id:"tconstruct:cast_custom",Count:1b,Damage:0s},{Slot:14b,id:"mob_grinding_utils:fan_upgrade",Count:6b,Damage:0s},{Slot:15b,id:"minecraft:end_stone",Count:4b,Damage:0s},{Slot:16b,id:"mob_grinding_utils:saw_upgrade",Count:10b,Damage:0s},{Slot:17b,id:"minecraft:dirt",Count:59b,Damage:0s},{Slot:18b,id:"minecraft:cobblestone",Count:64b,Damage:0s},{Slot:19b,id:"minecraft:cobblestone",Count:64b,Damage:0s},{Slot:22b,id:"mob_grinding_utils:fan",Count:2b,Damage:0s},{Slot:24b,ForgeCaps:{"astralsorcery:cap_item_amulet_holder":{}},id:"thermalfoundation:wrench",Count:1b,Damage:0s},{Slot:25b,id:"mob_grinding_utils:saw_upgrade",Count:10b,Damage:1s},{Slot:26b,ForgeCaps:{"astralsorcery:cap_item_amulet_holder":{}},id:"randomthings:timeinabottle",Count:1b,tag:{timeData:{storedTime:40600}},Damage:0s},{Slot:27b,id:"minecraft:dirt",Count:64b,Damage:0s},{Slot:28b,id:"minecraft:dirt",Count:64b,Damage:0s},{Slot:29b,id:"minecraft:cobblestone",Count:59b,Damage:0s},{Slot:30b,id:"minecraft:lever",Count:2b,Damage:0s},{Slot:31b,id:"ftbquests:screen",Count:1b,tag:{BlockEntityTag:{Task:-113945064,InputOnly:1b,id:"ftbquests:screen_core"},display:{Lore:["(+NBT)"]}},Damage:0s},{Slot:32b,id:"minecraft:cobblestone",Count:64b,Damage:0s},{Slot:33b,id:"minecraft:cobblestone",Count:64b,Damage:0s},{Slot:34b,id:"minecraft:cobblestone",Count:64b,Damage:0s},{Slot:35b,id:"minecraft:cobblestone",Count:64b,Damage:0s}]}}